artek/__init__.py
artek/webanalytics/__init__.py
artek/webanalytics/activity.py
artek/webanalytics/apps.py
artek/webanalytics/templates/artek/webanalytics/_adwords_conversion.html
artek/webanalytics/templates/artek/webanalytics/_gauges.html
artek/webanalytics/templates/artek/webanalytics/_google.html
artek/webanalytics/templates/artek/webanalytics/_mixpanel.html
artek/webanalytics/templatetags/__init__.py
artek/webanalytics/templatetags/artek_webanalytics_tags.py
artek/webanalytics/tests/__init__.py
artek/webanalytics/tests/models.py
artek/webanalytics/tests/tests.py
artek/webanalytics/tests/urls.py
artek_webanalytics-4.0.2.dist-info/METADATA
artek_webanalytics-4.0.2.dist-info/WHEEL
artek_webanalytics-4.0.2.dist-info/top_level.txt
artek_webanalytics-4.0.2.dist-info/RECORD
